{
  "formdata": [
    {
      "name": "fd",
      "email": "koonlucky123@gmail.com",
      "message": "เย่",
      "id": 1
    },
    {
      "name": "fd1",
      "email": "koonlucky123@gmail.com",
      "message": "เย่ๆ",
      "id": 2
    },
    {
      "name": "art",
      "email": "art123@gmail.com",
      "message": "เก่งมากครับ",
      "id": 3
    },
    {
      "name": "ลัคกี้",
      "email": "koonlucky555@gmail.com",
      "message": "เทสกล่องข้อความแบบยาวๆๆ .",
      "id": 4
    }
  ]
}